jacked/__init__.py
jacked/cli.py
jacked/client.py
jacked/config.py
jacked/indexer.py
jacked/retriever.py
jacked/searcher.py
jacked/transcript.py
jacked/data/agents/code-simplicity-reviewer.md
jacked/data/agents/defensive-error-handler.md
jacked/data/agents/double-check-reviewer.md
jacked/data/agents/git-pr-workflow-manager.md
jacked/data/agents/issue-pr-coordinator.md
jacked/data/agents/pr-workflow-checker.md
jacked/data/agents/readme-maintainer.md
jacked/data/agents/test-coverage-engineer.md
jacked/data/agents/test-coverage-improver.md
jacked/data/agents/wiki-documentation-architect.md
jacked/data/commands/dc.md
jacked/data/commands/pr.md
jacked/data/skills/jacked/SKILL.md
claude_jacked-0.2.7.dist-info/METADATA
claude_jacked-0.2.7.dist-info/WHEEL
claude_jacked-0.2.7.dist-info/entry_points.txt
claude_jacked-0.2.7.dist-info/licenses/LICENSE
claude_jacked-0.2.7.dist-info/RECORD
