Metadata-Version: 2.4
Name: claude-jacked
Version: 0.2.7
Summary: Cross-machine semantic search for Claude Code sessions
Project-URL: Homepage, https://github.com/jackneil/claude-jacked
Project-URL: Repository, https://github.com/jackneil/claude-jacked
Project-URL: Issues, https://github.com/jackneil/claude-jacked/issues
Author-email: Jack Neil <jack@jackmd.com>
License-Expression: MIT
License-File: LICENSE
Keywords: ai,claude,context,qdrant,semantic-search
Classifier: Development Status :: 4 - Beta
Classifier: Intended Audience :: Developers
Classifier: License :: OSI Approved :: MIT License
Classifier: Programming Language :: Python :: 3
Classifier: Programming Language :: Python :: 3.10
Classifier: Programming Language :: Python :: 3.11
Classifier: Programming Language :: Python :: 3.12
Requires-Python: >=3.10
Requires-Dist: click>=8.0.0
Requires-Dist: python-dotenv>=1.0.0
Requires-Dist: qdrant-client>=1.7.0
Requires-Dist: rich>=13.0.0
Provides-Extra: dev
Requires-Dist: pytest-cov>=4.0.0; extra == 'dev'
Requires-Dist: pytest>=7.0.0; extra == 'dev'
